[
  {
    "BookId": 17,
    "Name": "Harry Potter",
    "Pages": 267,
    "Price": 2.99,
    "PublishDate": null,
    "Genre": 1,
    "Author": { "AuthorId": 109, "Name": "A.B. Author" },
    "Reviews": null
  },
  {
    "BookId": 54,
    "Name": "Memory Man",
    "Pages": 560,
    "Price": 1.99,
    "PublishDate": null,
    "Genre": 0,
    "Author": { "AuthorId": 10, "Name": "C.D. Author" },
    "Reviews": null
  },
  {
    "BookId": 66,
    "Name": "Exhalation",
    "Pages": 368,
    "Price": 2.99,
    "PublishDate": null,
    "Genre": 2,
    "Author": { "AuthorId": 1, "Name": "E.F. Author" },
    "Reviews": [
      {
        "ReviewId": 6,
        "Rating": 5,
        "Description": "A description",
        "ReviewDate": "0001-01-01T00:00:00",
        "User": "Some user"
      },
      {
        "ReviewId": 14,
        "Rating": 3,
        "Description": "A description",
        "ReviewDate": "0001-01-01T00:00:00",
        "User": "Some user"
      }
    ]
  },
  {
    "BookId": 100,
    "Name": "Test book",
    "Pages": 123,
    "Price": 5.99,
    "PublishDate": null,
    "Genre": 0,
    "Author": { "AuthorId": 19, "Name": "G.H. Author" },
    "Reviews": [
      {
        "ReviewId": 6,
        "Rating": 5,
        "Description": "A description",
        "ReviewDate": "0001-01-01T00:00:00",
        "User": "Some user"
      }
    ]
  },
  {
    "BookId": 4092,
    "Name": "A new book",
    "Pages": 100,
    "Price": 9.99,
    "PublishDate": "2000-12-12T05:00:00Z",
    "Genre": 3,
    "Author": null,
    "Reviews": null
  }
]
